mfd_testing/__init__.py
mfd_testing/mfd_testing.py
mfd_testing-6.17.2.dist-info/METADATA
mfd_testing-6.17.2.dist-info/WHEEL
mfd_testing-6.17.2.dist-info/top_level.txt
mfd_testing-6.17.2.dist-info/RECORD
