Metadata-Version: 2.4
Name: mfd-testing
Version: 6.17.2
Summary: Module for a code quality related scripts.
Project-URL: Homepage, https://github.com/pmarusz/mfd-testing
Requires-Python: <3.14,>=3.10
Requires-Dist: pytest<9,>=7.2.1
Requires-Dist: pytest-cov~=5.0.0
Requires-Dist: pytest-xdist~=3.6.1
Requires-Dist: coverage~=7.3.0
Requires-Dist: diff-cover<9,>=8.0.3
Requires-Dist: pre-commit
Requires-Dist: ruff==0.4.7
Requires-Dist: setuptools
